{
  "project_info": {
    "project_number": "82664229069",
    "project_id": "los-pollos-a9354",
    "storage_bucket": "los-pollos-a9354.firebasestorage.app"
  },
  "client": [
    {
      "client_info": {
        "mobilesdk_app_id": "1:82664229069:android:60aabc96b9ea5a7db20184",
        "android_client_info": {
          "package_name": "com.example.los_pollos_hermanos"
        }
      },
      "oauth_client": [],
      "api_key": [
        {
          "current_key": "AIzaSyCDN9XmN6rW_THEVe4mTPFFJy3psC3GMZE"
        }
      ],
      "services": {
        "appinvite_service": {
          "other_platform_oauth_client": []
        }
      }
    }
  ],
  "configuration_version": "1"
}